[
    {
        "postId": 101,
        "commentId": 1,
        "username": "John Doe",
        "profile_picture": "/images/profileIcon/image.jpg",
        "comment": "This is a great post! Thanks for sharing.",
        "replies": [
            {
                "commentId": 2,
                "username": "Jane Doe",
                "profile_picture": "/images/profileIcon/image.jpg",
                "comment": "I agree! Very informative."
            },
            {
                "commentId": 6,
                "username": "Michael Scott",
                "profile_picture": "/images/profileIcon/image.jpg",
                "comment": "Absolutely! This needs more attention."
            }
        ]
    },
    {
        "postId": 101,
        "commentId": 3,
        "username": "Alice Brown",
        "profile_picture": "/images/profileIcon/image.jpg",
        "comment": "Does anyone have more details on this?",
        "replies": [
            {
                "commentId": 7,
                "username": "Robert King",
                "profile_picture": "/images/profileIcon/image.jpg",
                "comment": "I found some articles related to this. Want me to share?"
            }
        ]
    },
    {
        "postId": 102,
        "commentId": 4,
        "username": "Mark Smith",
        "profile_picture": "/images/profileIcon/image.jpg",
        "comment": "I have a different perspective on this topic.",
        "replies": [
            {
                "commentId": 5,
                "username": "Emily Johnson",
                "profile_picture": "/images/profileIcon/image.jpg",
                "comment": "Interesting take, Mark! Could you elaborate?"
            }
        ]
    },
    {
        "postId": 101,
        "commentId": 8,
        "username": "Chris Evans",
        "profile_picture": "/images/profileIcon/image.jpg",
        "comment": "This is exactly what I was looking for!",
        "replies": [ ]
    },
    {
        "postId": 103,
        "commentId": 9,
        "username": "Sophia Carter",
        "profile_picture": "/images/profileIcon/image.jpg",
        "comment": "Not sure if I agree with this. Could someone clarify?",
        "replies": [
            {
                "commentId": 10,
                "username": "David Lee",
                "profile_picture": "/images/profileIcon/image.jpg",
                "comment": "What part do you disagree with? Happy to discuss!"
            },
            {
                "commentId": 11,
                "username": "Rachel Green",
                "profile_picture": "/images/profileIcon/image.jpg",
                "comment": "I think the main point is valid, but the data could be better."
            }
        ]
    },
    {
        "postId": 102,
        "commentId": 12,
        "username": "Ethan Hunt",
        "profile_picture": "/images/profileIcon/image.jpg",
        "comment": "Does anyone know when this update was released?",
        "replies": [
            {
                "commentId": 13,
                "username": "Lara Croft",
                "profile_picture": "/images/profileIcon/image.jpg",
                "comment": "I believe it was last month, but let me double-check."
            }
        ]
    },
    {
        "postId": 101,
        "commentId": 14,
        "username": "Tom Hardy",
        "profile_picture": "/images/profileIcon/image.jpg",
        "comment": "This article really helped me. Thanks!",
        "replies": [ ]
    },
    {
        "postId": 102,
        "commentId": 15,
        "username": "Dwayne Johnson",
        "profile_picture": "/images/profileIcon/image.jpg",
        "comment": "Strong points made in this post.",
        "replies": [
            {
                "commentId": 16,
                "username": "Kevin Hart",
                "profile_picture": "/images/profileIcon/image.jpg",
                "comment": "Agreed! Some really useful insights."
            }
        ]
    }
]
